happenings/__init__.py
happenings/core.py
happenings/event.py
happenings/event_calendar.py
happenings/utils.py
happenings-0.0.4.dist-info/LICENSE
happenings-0.0.4.dist-info/METADATA
happenings-0.0.4.dist-info/WHEEL
happenings-0.0.4.dist-info/top_level.txt
happenings-0.0.4.dist-info/RECORD
