Metadata-Version: 2.1
Name: happenings
Version: 0.0.4
Summary: A utility package for creating complex event based time-series data
Home-page: https://github.com/TNonet/happenings
Author: Tim Nonet
Author-email: tim.nonet@gmail.com
License: UNKNOWN
Project-URL: Bug Tracker, https://github.com/TNonet/happenings/issues
Platform: UNKNOWN
Classifier: Programming Language :: Python :: 3
Classifier: License :: OSI Approved :: MIT License
Classifier: Operating System :: OS Independent
Requires-Python: >=3.7
Requires-Dist: numpy (>=1.19.0)
Requires-Dist: scipy (>=1.1.0)
Requires-Dist: pandas (>=1.0.0)
Requires-Dist: python-dateutil
Provides-Extra: test
Requires-Dist: attrs (>=19.2.0) ; extra == 'test'
Requires-Dist: hypothesis ; extra == 'test'
Requires-Dist: pytest ; extra == 'test'
